bver.py
bver-0.1.2.dist-info/LICENSE
bver-0.1.2.dist-info/METADATA
bver-0.1.2.dist-info/WHEEL
bver-0.1.2.dist-info/top_level.txt
bver-0.1.2.dist-info/RECORD
