Metadata-Version: 2.1
Name: bver
Version: 0.1.2
Summary: A simple Bible translation parser for human input
Home-page: https://code.theres.life/heb12/bver
Author: MotS
Author-email: ted.jameson@pm.me
License: UNKNOWN
Keywords: bible,json,parser
Platform: UNKNOWN
